pydantic_logic/__init__.py
pydantic_logic/expression.py
pydantic_logic/logic.py
pydantic_logic-1.0.3.dist-info/LICENSE
pydantic_logic-1.0.3.dist-info/METADATA
pydantic_logic-1.0.3.dist-info/WHEEL
pydantic_logic-1.0.3.dist-info/RECORD
