Metadata-Version: 2.1
Name: pydantic-logic
Version: 1.0.3
Summary: Build complex rules, operate them with Pydantic, and execute them in Python
Home-page: https://github.com/barabum0/pydantic-logic
License: MIT
Keywords: python,pydantic,logic,condition,validation,json
Author: Roman Poltorabatko
Author-email: r.m.poltorabatko@gmail.com
Requires-Python: >=3.10,<4.0
Classifier: Intended Audience :: Developers
Classifier: License :: OSI Approved :: MIT License
Classifier: Operating System :: OS Independent
Classifier: Programming Language :: Python
Classifier: Programming Language :: Python :: 3
Classifier: Programming Language :: Python :: 3.10
Classifier: Programming Language :: Python :: 3.11
Classifier: Programming Language :: Python :: 3.12
Classifier: Topic :: Software Development :: Libraries :: Python Modules
Requires-Dist: pydantic (>=2.0)
Project-URL: Repository, https://github.com/barabum0/pydantic-logic
